pixel8/__init__.py
pixel8/cli.py
pixel8/core.py
pixel8/edges.py
pixel8-1.0.0.dist-info/licenses/LICENSE
pixel8-1.0.0.dist-info/METADATA
pixel8-1.0.0.dist-info/WHEEL
pixel8-1.0.0.dist-info/entry_points.txt
pixel8-1.0.0.dist-info/top_level.txt
pixel8-1.0.0.dist-info/RECORD
