Metadata-Version: 2.4
Name: pixel8
Version: 1.0.0
Summary: Generate pixel art from images using Canny edge detection
Author-email: Mehul Arora <aroramehul8@gmail.com>
License-Expression: MIT
Project-URL: Homepage, https://github.com/mehularora8/pixel8
Project-URL: Repository, https://github.com/mehularora8/pixel8
Project-URL: Issues, https://github.com/mehularora8/pixel8/issues
Keywords: pixel-art,image-processing,canny-edge-detection,computer-vision
Classifier: Development Status :: 3 - Alpha
Classifier: Intended Audience :: Developers
Classifier: Intended Audience :: End Users/Desktop
Classifier: Programming Language :: Python :: 3
Classifier: Programming Language :: Python :: 3.8
Classifier: Programming Language :: Python :: 3.9
Classifier: Programming Language :: Python :: 3.10
Classifier: Programming Language :: Python :: 3.11
Classifier: Programming Language :: Python :: 3.12
Classifier: Topic :: Multimedia :: Graphics :: Graphics Conversion
Classifier: Topic :: Scientific/Engineering :: Image Processing
Requires-Python: >=3.8
License-File: LICENSE
Requires-Dist: numpy>=1.19.0
Requires-Dist: matplotlib>=3.3.0
Requires-Dist: scikit-image>=0.18.0
Requires-Dist: Pillow>=8.0.0
Provides-Extra: dev
Requires-Dist: pytest>=6.0; extra == "dev"
Requires-Dist: black>=22.0; extra == "dev"
Requires-Dist: flake8>=4.0; extra == "dev"
Requires-Dist: mypy>=0.910; extra == "dev"
Dynamic: license-file
